{
    "build": {
        "context": ".",
        "dockerfile": "Dockerfile"
    },
    "customizations": {
        "vscode": {
            "extensions": [
                "dgileadi.java-decompiler",
                "eamodio.gitlens",
                "redhat.vscode-yaml",
                "shardulm94.trailing-spaces",
                "SonarSource.sonarlint-vscode",
                "vmware.vscode-boot-dev-pack",
                "vscjava.vscode-java-pack"
            ],
            "settings": {
                "java.compile.nullAnalysis.mode": "automatic",
                "java.configuration.updateBuildConfiguration": "interactive"
            }
        }
    }
}
